pynojector/__init__.py
pynojector/trainscanner_plugins/conformal.py
pynojector/trainscanner_plugins/square_pano.py
pynojector/trainscanner_plugins/swirl.py
pynojector-0.4.0.dist-info/LICENSE
pynojector-0.4.0.dist-info/METADATA
pynojector-0.4.0.dist-info/WHEEL
pynojector-0.4.0.dist-info/entry_points.txt
pynojector-0.4.0.dist-info/RECORD
