Metadata-Version: 2.3
Name: pynojector
Version: 0.4.0
Summary: 
Author: vitroid
Author-email: vitroid@gmail.com
Requires-Python: >=3.11,<4.0
Classifier: Programming Language :: Python :: 3
Classifier: Programming Language :: Python :: 3.11
Classifier: Programming Language :: Python :: 3.12
Classifier: Programming Language :: Python :: 3.13
Requires-Dist: numpy (>=2.2.5,<3.0.0)
Requires-Dist: opencv-python-headless (>=4.11.0.86,<5.0.0.0)
Requires-Dist: scipy (>=1.15.3,<2.0.0)
Requires-Dist: tiffeditor (>=0.2.0,<0.3.0)
Requires-Dist: tqdm (>=4.67.1,<5.0.0)
